sqlogging/__init__.py
sqlogging/benchmark.py
sqlogging/logging.py
sqlogging/test_logging.py
sqlite_logging-0.0.4.dist-info/LICENSE
sqlite_logging-0.0.4.dist-info/METADATA
sqlite_logging-0.0.4.dist-info/WHEEL
sqlite_logging-0.0.4.dist-info/top_level.txt
sqlite_logging-0.0.4.dist-info/RECORD
