Metadata-Version: 2.1
Name: sqlite-logging
Version: 0.0.4
Summary: SQLite3-based logging for Python
Author-email: Brandon Rohrer <brohrer@gmail.com>
Project-URL: Repository, https://github.com/brohrer/sqlogging
Classifier: Programming Language :: Python :: 3
Classifier: License :: OSI Approved :: MIT License
Classifier: Operating System :: OS Independent
Requires-Python: >=3.8
License-File: LICENSE
